Workbook

Sheet Início
C3: A ESTRATÉGIA QUE MUDOU A MINHA VIDA · TRADER BRUNO BORGES
C4: Diário de Execução 40P
C7: Registre cada operação. Entenda seus padrões. Evolua com método.
C11: Como usar em 4 passos
C12: 1 · Registre | F12: 2 · Escolha | I12: 3 · Revise | L12: 4 · Evolua
C13: Depois de cada operação, preencha uma linha na aba Diário. | F13: Use as listas suspensas e escreva o resultado em pontos. | I13: Anote o erro cometido e o que pode fazer diferente. | L13: Veja seus padrões na aba Painel, atualizada sozinha.
C17: As 6 etapas do Mapa de Decisão 40P
C18: 1 · Cenário | E18: 2 · Plataforma | G18: 3 · Gatilho | I18: 4 · Gestão | K18: 5 · Saída | M18: 6 · Revisão
C19: O preço está em tendência e onde estão as regiões? | E19: Está tudo configurado no Profit? | G19: O preço voltou à região de 50% a favor da tendência? | I19: A parcial foi executada? | K19: A tendência continua a favor? | M19: O que essa operação ensinou?
C23: Exemplo de preenchimento (valores ilustrativos)
C24: Campo | F24: Como preencher | L24: Exemplo
C25: Data | F25: Dia da operação. | L25: 14/10/2026
C26: Hora | F26: Horário da entrada. | L26: 10:15
C27: Compra ou venda | F27: Sentido da operação. | L27: Compra
C28: Contratos | F28: Mínimo de 5. | L28: 5
C29: Tendência definida? | F29: Você conseguiu apontar o topo ou fundo que define a tendência? | L29: Sim
C30: Motivo da entrada | F30: Qual gatilho levou à entrada. | L30: Pullback
C31: Stop e alvo definidos antes? | F31: Stop e alvo estavam definidos antes da entrada? | L31: Sim
C32: Tipo de saída | F32: Como a operação terminou. | L32: Alvo final
C33: Resultado (pontos) | F33: Pontos totais da operação. Perda com sinal de menos. | L33: 500
C34: Emoção ao entrar | F34: Escolha na lista. | L34: Confiante
C35: Emoção ao sair | F35: Escolha na lista. | L35: Calmo
C36: Erro cometido | F36: Em uma frase. Deixe em branco se não houve. | L36: Nenhum
C37: O que posso fazer diferente? | F37: Qual ajuste operacional ou emocional devo fazer para a próxima operação. | L37: Esperar a região de 50%
C39: As listas de emoções, motivos e saídas podem ser editadas na aba Listas. A lista de emoções é uma sugestão inicial.
C40: Material educacional. Não é recomendação de compra ou venda de ativos nem promessa de resultado; operar no mercado financeiro envolve risco de perda.

Sheet Diário
B1: Diário de Execução 40P
B3: Operação | G3: Cenário | J3: Saída | L3: 6 · Revisão
B4: Nº | C4: Data | D4: Hora | E4: Compra ou venda | F4: Contratos | G4: Tendência definida? | H4: Motivo da entrada | I4: Stop e alvo definidos antes? | J4: Tipo de saída | K4: Resultado (pontos) | L4: Emoção ao entrar | M4: Emoção ao sair | N4: Erro cometido | O4: O que posso fazer diferente?
B5: 1 | C5: 46286 | D5: 0.38541667 | E5: Compra | F5: 5 | G5: Sim | H5: Ponto de parada | I5: Sim | J5: Alvo final | K5: 500 | L5: Confiante | M5: Calmo | N5: Sem erros cometidos | O5: Sem observações
B6: =IF(C6="","",ROW()-5)
B7: =IF(C7="","",ROW()-5)
B8: =IF(C8="","",ROW()-5)
B9: =IF(C9="","",ROW()-5)
B10: =IF(C10="","",ROW()-5)
B11: =IF(C11="","",ROW()-5)
B12: =IF(C12="","",ROW()-5)
B13: =IF(C13="","",ROW()-5)
B14: =IF(C14="","",ROW()-5)
B15: =IF(C15="","",ROW()-5)
B16: =IF(C16="","",ROW()-5)
B17: =IF(C17="","",ROW()-5)
... B204: =IF(C204="","",ROW()-5)

Sheet Painel
C2: Painel
C3: Seus números e padrões, atualizados sozinhos a cada linha do Diário
C6: OPERAÇÕES REGISTRADAS | F6: RESULTADO TOTAL (PONTOS) | I6: MÉDIA POR OPERAÇÃO (PONTOS) | L6: OPERAÇÕES POSITIVAS
C7: =Tabelas!C5 -> 1 | F7: =Tabelas!C6 -> 500 | I7: =Tabelas!C7 -> 500 | L7: =IFERROR(Tabelas!C8/Tabelas!C5,"-") -> 1
C10: RESULTADO POSITIVO (Nº) | F10: RESULTADO NEGATIVO (Nº) | I10: MELHOR OPERAÇÃO (PONTOS) | L10: PIOR OPERAÇÃO (PONTOS)
C11: =Tabelas!C8 -> 1 | F11: =Tabelas!C9 -> 0 | I11: =IF(Tabelas!$C$5=0,"-",MAX(Diário!$K$5:$K$204)) -> 500 | L11: =IF(Tabelas!$C$5=0,"-",MIN(Diário!$K$5:$K$204)) -> 500
C14: Leitura do painel
C15: ▸ | D15: =IF(Tabelas!$C$5=0,"Registre operações na aba Diário e este painel passa a mostrar a sua leitura.","Você registrou "&Tabelas!$C$5&" operações: "&Tabelas!C8&" positivas e "&Tabelas!C9&" negativas.") -> Você registrou 1 operações: 1 positivas e 0 negativas.
C16: ▸ | D16: =IF(Tabelas!$C$5=0,"","Quando a tendência estava definida, a média foi de "&IFERROR(ROUND(Tabelas!D12,1)&" pontos","(sem dados)")&"; quando não estava, "&IFERROR(ROUND(Tabelas!E12,1)&" pontos","(sem dados)")&".") -> Quando a tendência estava definida, a média foi de 500 pontos; quando não estava, (sem dados).
C17: ▸ | D17: =IF(Tabelas!$C$5=0,"","Com stop e alvo definidos antes, a média foi de "&IFERROR(ROUND(Tabelas!D13,1)&" pontos","(sem dados)")&"; sem eles, "&IFERROR(ROUND(Tabelas!E13,1)&" pontos","(sem dados)")&".") -> Com stop e alvo definidos antes, a média foi de 500 pontos; sem eles, (sem dados).
C18: ▸ | D18: =IF(MAX(Tabelas!C29:C40)=0,"","Emoção mais frequente ao entrar: "&INDEX(Tabelas!B29:B40,MATCH(MAX(Tabelas!C29:C40),Tabelas!C29:C40,0))&".") -> Emoção mais frequente ao entrar: Confiante.
C20: Gráficos
C54: Material educacional. Não é recomendação de compra ou venda de ativos nem promessa de resultado; operar no mercado financeiro envolve risco de perda.

Sheet Tabelas
B1: Tabelas de apoio
B2: Calculadas sozinhas a partir do Diário. Alimentam o Painel. Não digite nada aqui.
B4: Visão geral
B5: Operações registradas | C5: =COUNT(Diário!$C$5:$C$204) -> 1
B6: Resultado total (pontos) | C6: =SUM(Diário!$K$5:$K$204) -> 500
B7: Resultado médio por operação (pontos) | C7: =IFERROR(AVERAGE(Diário!$K$5:$K$204),"-") -> 500
B8: Operações com resultado positivo | C8: =COUNTIF(Diário!$K$5:$K$204,">0") -> 1
B9: Operações com resultado negativo | C9: =COUNTIF(Diário!$K$5:$K$204,"<0") -> 0
B11: Regras do mapa | C11: % de "Sim" | D11: Média se "Sim" | E11: Média se "Não"
B12: 1 · Tendência definida? | C12: =IFERROR(COUNTIF(Diário!$G$5:$G$204,"Sim")/(COUNTIF(Diário!$G$5:$G$204,"Sim")+COUNTIF(Diário!$G$5:$G$204,"Não")),"-") -> 1 | D12: =IFERROR(AVERAGEIFS(Diário!$K$5:$K$204,Diário!$G$5:$G$204,"Sim"),"-") -> 500 | E12: =IFERROR(AVERAGEIFS(Diário!$K$5:$K$204,Diário!$G$5:$G$204,"Não"),"-") -> -
B13: 3 · Stop e alvo definidos antes? | C13: =IFERROR(COUNTIF(Diário!$I$5:$I$204,"Sim")/(COUNTIF(Diário!$I$5:$I$204,"Sim")+COUNTIF(Diário!$I$5:$I$204,"Não")),"-") -> 1 | D13: =IFERROR(AVERAGEIFS(Diário!$K$5:$K$204,Diário!$I$5:$I$204,"Sim"),"-") -> 500 | E13: =IFERROR(AVERAGEIFS(Diário!$K$5:$K$204,Diário!$I$5:$I$204,"Não"),"-") -> -
B14: Médias em pontos por operação.
B16: Motivo da entrada | C16: Operações | D16: Pontos totais
B17: =Listas!C5 -> Pullback | C17: =COUNTIF(Diário!$H$5:$H$204,$B17) -> 0 | D17: =SUMIFS(Diário!$K$5:$K$204,Diário!$H$5:$H$204,$B17) -> 0
B18: =Listas!C6 -> Ponto de parada | C18: =COUNTIF(Diário!$H$5:$H$204,$B18) -> 1 | D18: =SUMIFS(Diário!$K$5:$K$204,Diário!$H$5:$H$204,$B18) -> 500
B19: =Listas!C7 -> Negação | C19: =COUNTIF(Diário!$H$5:$H$204,$B19) -> 0 | D19: =SUMIFS(Diário!$K$5:$K$204,Diário!$H$5:$H$204,$B19) -> 0
B20: =Listas!C8 -> Rompimento sem teste | C20: =COUNTIF(Diário!$H$5:$H$204,$B20) -> 0 | D20: =SUMIFS(Diário!$K$5:$K$204,Diário!$H$5:$H$204,$B20) -> 0
B22: Como as operações terminaram | C22: Operações | D22: Pontos totais
B23: =Listas!D5 -> Alvo final | C23: =COUNTIF(Diário!$J$5:$J$204,$B23) -> 1 | D23: =SUMIFS(Diário!$K$5:$K$204,Diário!$J$5:$J$204,$B23) -> 500
B24: =Listas!D6 -> Stop | C24: =COUNTIF(Diário!$J$5:$J$204,$B24) -> 0 | D24: =SUMIFS(Diário!$K$5:$K$204,Diário!$J$5:$J$204,$B24) -> 0
B25: =Listas!D7 -> Primeiro alvo (tendência contra) | C25: =COUNTIF(Diário!$J$5:$J$204,$B25) -> 0 | D25: =SUMIFS(Diário!$K$5:$K$204,Diário!$J$5:$J$204,$B25) -> 0
B26: =Listas!D8 -> Saída manual | C26: =COUNTIF(Diário!$J$5:$J$204,$B26) -> 0 | D26: =SUMIFS(Diário!$K$5:$K$204,Diário!$J$5:$J$204,$B26) -> 0
B28: Emoções | C28: Ao entrar | D28: Ao sair | E28: Média (pts) ao entrar
B29: =Listas!B5 -> Calmo | C29: =COUNTIF(Diário!$L$5:$L$204,$B29) -> 0 | D29: =COUNTIF(Diário!$M$5:$M$204,$B29) -> 1 | E29: =IFERROR(AVERAGEIFS(Diário!$K$5:$K$204,Diário!$L$5:$L$204,$B29),"-") -> -
B30: =Listas!B6 -> Confiante | C30: =COUNTIF(Diário!$L$5:$L$204,$B30) -> 1 | D30: =COUNTIF(Diário!$M$5:$M$204,$B30) -> 0 | E30: =IFERROR(AVERAGEIFS(Diário!$K$5:$K$204,Diário!$L$5:$L$204,$B30),"-") -> 500
B31: =Listas!B7 -> Focado | C31: =COUNTIF(Diário!$L$5:$L$204,$B31) -> 0 | D31: =COUNTIF(Diário!$M$5:$M$204,$B31) -> 0 | E31: =IFERROR(AVERAGEIFS(Diário!$K$5:$K$204,Diário!$L$5:$L$204,$B31),"-") -> -
B32: =Listas!B8 -> Ansioso | C32: =COUNTIF(Diário!$L$5:$L$204,$B32) -> 0 | D32: =COUNTIF(Diário!$M$5:$M$204,$B32) -> 0 | E32: =IFERROR(AVERAGEIFS(Diário!$K$5:$K$204,Diário!$L$5:$L$204,$B32),"-") -> -
B33: =Listas!B9 -> Impaciente | C33: =COUNTIF(Diário!$L$5:$L$204,$B33) -> 0 | D33: =COUNTIF(Diário!$M$5:$M$204,$B33) -> 0 | E33: =IFERROR(AVERAGEIFS(Diário!$K$5:$K$204,Diário!$L$5:$L$204,$B33),"-") -> -
B34: =Listas!B10 -> Com medo | C34: =COUNTIF(Diário!$L$5:$L$204,$B34) -> 0 | D34: =COUNTIF(Diário!$M$5:$M$204,$B34) -> 0 | E34: =IFERROR(AVERAGEIFS(Diário!$K$5:$K$204,Diário!$L$5:$L$204,$B34),"-") -> -
B35: =Listas!B11 -> Ganancioso | C35: =COUNTIF(Diário!$L$5:$L$204,$B35) -> 0 | D35: =COUNTIF(Diário!$M$5:$M$204,$B35) -> 0 | E35: =IFERROR(AVERAGEIFS(Diário!$K$5:$K$204,Diário!$L$5:$L$204,$B35),"-") -> -
B36: =Listas!B12 -> Eufórico | C36: =COUNTIF(Diário!$L$5:$L$204,$B36) -> 0 | D36: =COUNTIF(Diário!$M$5:$M$204,$B36) -> 0 | E36: =IFERROR(AVERAGEIFS(Diário!$K$5:$K$204,Diário!$L$5:$L$204,$B36),"-") -> -
B37: =Listas!B13 -> Frustrado | C37: =COUNTIF(Diário!$L$5:$L$204,$B37) -> 0 | D37: =COUNTIF(Diário!$M$5:$M$204,$B37) -> 0 | E37: =IFERROR(AVERAGEIFS(Diário!$K$5:$K$204,Diário!$L$5:$L$204,$B37),"-") -> -
B38: =Listas!B14 -> Irritado | C38: =COUNTIF(Diário!$L$5:$L$204,$B38) -> 0 | D38: =COUNTIF(Diário!$M$5:$M$204,$B38) -> 0 | E38: =IFERROR(AVERAGEIFS(Diário!$K$5:$K$204,Diário!$L$5:$L$204,$B38),"-") -> -
B39: =Listas!B15 -> Indiferente | C39: =COUNTIF(Diário!$L$5:$L$204,$B39) -> 0 | D39: =COUNTIF(Diário!$M$5:$M$204,$B39) -> 0 | E39: =IFERROR(AVERAGEIFS(Diário!$K$5:$K$204,Diário!$L$5:$L$204,$B39),"-") -> -
B40: =Listas!B16 -> Outra | C40: =COUNTIF(Diário!$L$5:$L$204,$B40) -> 0 | D40: =COUNTIF(Diário!$M$5:$M$204,$B40) -> 0 | E40: =IFERROR(AVERAGEIFS(Diário!$K$5:$K$204,Diário!$L$5:$L$204,$B40),"-") -> -

Sheet Listas
B1: Listas editáveis
B2: Edite os textos abaixo e as listas suspensas do Diário e as contagens do Painel acompanham. Não apague linhas.
B4: Emoções | C4: Motivos de entrada | D4: Tipos de saída
B5: Calmo | C5: Pullback | D5: Alvo final
B6: Confiante | C6: Ponto de parada | D6: Stop
B7: Focado | C7: Negação | D7: Primeiro alvo (tendência contra)
B8: Ansioso | C8: Rompimento sem teste | D8: Saída manual
B9: Impaciente
B10: Com medo
B11: Ganancioso
B12: Eufórico
B13: Frustrado
B14: Irritado
B15: Indiferente
B16: Outra
